superdupper/core/__init__.py
superdupper/core/models.py
superdupper/services/__init__.py
superdupper/services/handlers.py
superdupper_core-0.0.14.dist-info/METADATA
superdupper_core-0.0.14.dist-info/WHEEL
superdupper_core-0.0.14.dist-info/top_level.txt
superdupper_core-0.0.14.dist-info/RECORD
