Metadata-Version: 2.1
Name: superdupper-core
Version: 0.0.14
Summary: Superdupper core.
